treat2p/__init__.py
treat2p/calculations.py
treat2p/core.py
treat2p/corrections.py
treat2p/normalisation.py
treat2p/utils.py
treat2p-0.0.5.dist-info/METADATA
treat2p-0.0.5.dist-info/WHEEL
treat2p-0.0.5.dist-info/top_level.txt
treat2p-0.0.5.dist-info/RECORD
