Metadata-Version: 2.1
Name: treat2p
Version: 0.0.5
Summary: Projects specific python code pipeline for analysis
Home-page: https://gitlab.pasteur.fr/haisslab/analysis-packages/treat2p
Author: Timothé Jost-MOUSSEAU
Author-email: timothe.jost-mousseau@pasteur.com
License: MIT
Classifier: Development Status :: 3 - Alpha
Classifier: Intended Audience :: Developers
Classifier: License :: OSI Approved :: MIT License
Classifier: Programming Language :: Python :: 3
Classifier: Programming Language :: Python :: 3.6
Classifier: Programming Language :: Python :: 3.7
Classifier: Programming Language :: Python :: 3.8
Classifier: Programming Language :: Python :: 3.9
Classifier: Programming Language :: Python :: 3.10
Classifier: Programming Language :: Python :: 3.11
Requires-Dist: numpy >=1.23
Requires-Dist: scipy >=1.9
Requires-Dist: joblib >=1.1
